Workbook

Sheet Summary
A1: Random Forest — Test-Set Results (Phase 3)
A2: Model: models/rf_eff_rate.joblib | Data: data/processed/test.csv (frozen, hash-verified) | Generated 2026-07-22
A3: All metrics below are LIVE formulas over the Predictions sheet — they recompute if you edit/filter values there.
A5: Metric | B5: Value | C5: Note
A6: Test rows | B6: =COUNT(Predictions!B2:B12248) | C6: Should equal 12,247 (freeze manifest).
A7: R² | B7: =1-SUMPRODUCT(Predictions!D2:D12248,Predictions!D2:D12248)/SUMPRODUCT((Predictions!B2:B12248-AVERAGE(Predictions!B2:B12248))*(Predictions!B2:B12248-AVERAGE(Predictions!B2:B12248))) | C7: 1 − SS_residual / SS_total.
A8: MAE (rate points) | B8: =AVERAGE(Predictions!E2:E12248) | C8: Mean absolute error, in effective-rate points.
A9: Median abs error | B9: =MEDIAN(Predictions!E2:E12248) | C9: Half of filers are predicted at least this close.
A10: % within ±1 rate point | B10: =COUNTIF(Predictions!E2:E12248,"<=1")/COUNT(Predictions!E2:E12248)
A11: % within ±2 rate points | B11: =COUNTIF(Predictions!E2:E12248,"<=2")/COUNT(Predictions!E2:E12248)
A12: Train-set mean eff_rate (input) | B12: 5.310386 | C12: Error if we just predicted the train-set mean for everyone.
A14: Cross-check vs. models/rf_metrics.json (from the training notebook):
A15: R² = 0.9005, MAE = 1.2770 — the formulas above should reproduce these to 4 decimals.
A17: How to read this workbook
A18: Blue cells = data written in by the build (model predictions, frozen inputs). Black = live formulas.
A19: Predictions sheet: one row per test.csv filer, original frozen order. Columns B/C are the side-by-side you asked for;
A20: D (residual) is green when the model under-predicts, red when it over-predicts. Filter/sort with the header dropdowns.
A21: Income Deciles sheet: bias check across income levels (README §4.2) — all recomputed live from Predictions.
A22: Shares are fractions of unit income (68.0% = 0.68). filing_status/marst shown as labels, statefip as FIPS code.

Sheet Predictions
A1: test_row | B1: Actual eff_rate | C1: Predicted eff_rate | D1: Residual (actual − pred) | E1: Abs error | F1: unit_inctot | G1: filing_status | H1: marst | I1: statefip | J1: age | K1: nchild | L1: nchlt5 | M1: famsize | N1: wage_share | O1: business_share | P1: interest_share | Q1: dividend_share | R1: retirement_share | S1: socsec_share | T1: rent_share | U1: spouse_income_share | V1: asecwt
A2: 1 | B2: 3.1091434 | C2: 3.0706297 | D2: =B2-C2 | E2: =ABS(D2) | F2: 20102 | G2: single | H2: Never married/single | I2: 21 | J2: 26 | K2: 0 | L2: 0 | M2: 2 | N2: 0.99990051 | O2: 0 | P2: 9.9492588e-05 | Q2: 0 | R2: 0 | S2: 0 | T2: 0 | U2: 0 | V2: 4684.41
A3: 2 | B3: 7.792 | C3: 7.7910936 | D3: =B3-C3 | E3: =ABS(D3) | F3: 50000 | G3: single | H3: Widowed | I3: 46 | J3: 65 | K3: 0 | L3: 0 | M3: 1 | N3: 1 | O3: 0 | P3: 0 | Q3: 0 | R3: 0 | S3: 0 | T3: 0 | U3: 0 | V3: 692.59
A4: 3 | B4: 13.397097 | C4: 13.403025 | D4: =B4-C4 | E4: =ABS(D4) | F4: 210150 | G4: joint | H4: Married, spouse present | I4: 46 | J4: 39 | K4: 1 | L4: 0 | M4: 3 | N4: 0.71377587 | O4: 0 | P4: 0 | Q4: 0 | R4: 0 | S4: 0 | T4: 0 | U4: 0.28622413 | V4: 479.99
A5: 4 | B5: 9.5714656 | C5: 9.7807776 | D5: =B5-C5 | E5: =ABS(D5) | F5: 139355 | G5: joint | H5: Married, spouse present | I5: 36 | J5: 53 | K5: 1 | L5: 0 | M5: 3 | N5: 0.64583259 | O5: 0 | P5: 7.1759176e-06 | Q5: 0 | R5: 0 | S5: 0 | T5: 0 | U5: 0.35416024 | V5: 4069.75
A6: 5 | B6: 5.7475083 | C6: 6.1631673 | D6: =B6-C6 | E6: =ABS(D6) | F6: 36100 | G6: single | H6: Separated | I6: 28 | J6: 50 | K6: 1 | L6: 0 | M6: 4 | N6: 0.83102493 | O6: 0 | P6: 0.0027700831 | Q6: 0 | R6: 0 | S6: 0 | T6: 0 | U6: 0 | V6: 1099.96
A7: 6 | B7: 0.45570543 | C7: 1.9065858 | D7: =B7-C7 | E7: =ABS(D7) | F7: 36253 | G7: single | H7: Widowed | I7: 12 | J7: 80 | K7: 0 | L7: 0 | M7: 1 | N7: 0 | O7: 0 | P7: 0.13855405 | Q7: 0.00027583924 | R7: 0.019088075 | S7: 0.56105702 | T7: 0.16550354 | U7: 0 | V7: 3763.95
A8: 7 | B8: 4.9690807 | C8: 7.1804615 | D8: =B8-C8 | E8: =ABS(D8) | F8: 93450 | G8: joint | H8: Married, spouse present | I8: 46 | J8: 56 | K8: 0 | L8: 0 | M8: 2 | N8: 0 | O8: 0 | P8: 0.0053504548 | Q8: 0.01070091 | R8: 0 | S8: 0 | T8: 0.1070091 | U8: 0.44890316 | V8: 739.46
A9: 8 | B9: 6.2969697 | C9: 5.7567595 | D9: =B9-C9 | E9: =ABS(D9) | F9: 33000 | G9: single | H9: Divorced | I9: 13 | J9: 47 | K9: 0 | L9: 0 | M9: 1 | N9: 0.75757576 | O9: 0 | P9: 0.24242424 | Q9: 0 | R9: 0 | S9: 0 | T9: 0 | U9: 0 | V9: 2606.99
A10: 9 | B10: 7.7426301 | C10: 6.0593791 | D10: =B10-C10 | E10: =ABS(D10) | F10: 122594 | G10: joint | H10: Married, spouse present | I10: 51 | J10: 41 | K10: 2 | L10: 0 | M10: 4 | N10: 0.34259425 | O10: 0 | P10: 0.0012398649 | Q10: 0 | R10: 0 | S10: 0 | T10: 0 | U10: 0.65616588 | V10: 3109.47
A11: 10 | B11: 11.439316 | C11: 11.59646 | D11: =B11-C11 | E11: =ABS(D11) | F11: 191945 | G11: joint | H11: Married, spouse present | I11: 21 | J11: 44 | K11: 2 | L11: 0 | M11: 4 | N11: 0.20839303 | O11: 0 | P11: 1.0419651e-05 | Q11: 0 | R11: 0 | S11: 0 | T11: 0 | U11: 0.79159655 | V11: 1958.21
A12: 11 | B12: 3.2870594 | C12: 1.9234567 | D12: =B12-C12 | E12: =ABS(D12) | F12: 89107 | G12: joint | H12: Married, spouse present | I12: 24 | J12: 36 | K12: 2 | L12: 0 | M12: 5 | N12: 0.72946009 | O12: 0 | P12: 0 | Q12: 0 | R12: 0 | S12: 0 | T12: 0 | U12: 0.27053991 | V12: 1963.35
A13: 12 | B13: 5.7266667 | C13: 5.8406672 | D13: =B13-C13 | E13: =ABS(D13) | F13: 33400 | G13: single | H13: Never married/single | I13: 13 | J13: 19 | K13: 0 | L13: 0 | M13: 4 | N13: 0.89820359 | O13: 0 | P13: 0 | Q13: 0 | R13: 0 | S13: 0 | T13: 0 | U13: 0 | V13: 3286.31
... A12248: 12247 | B12248: 7.2406948 | C12248: 7.2071485 | D12248: =B12248-C12248 | E12248: =ABS(D12248) | F12248: 40300 | G12248: single | H12248: Never married/single | I12248: 39 | J12248: 26 | K12248: 0 | L12248: 0 | M12248: 1 | N12248: 0.99255583 | O12248: 0 | P12248: 0 | Q12248: 0.0074441687 | R12248: 0 | S12248: 0 | T12248: 0 | U12248: 0 | V12248: 6228.37

Sheet Income Deciles
A1: Decile | B1: Income from | C1: Income to | D1: Filers | E1: Mean residual | F1: MAE | G1: Mean actual | H1: Mean predicted
A2: 0 | B2: 1 | C2: 22000 | D2: =COUNTIFS(Predictions!F2:F12248,">="&B2,Predictions!F2:F12248,"<="&C2) | E2: =AVERAGEIFS(Predictions!D2:D12248,Predictions!F2:F12248,">="&B2,Predictions!F2:F12248,"<="&C2) | F2: =AVERAGEIFS(Predictions!E2:E12248,Predictions!F2:F12248,">="&B2,Predictions!F2:F12248,"<="&C2) | G2: =AVERAGEIFS(Predictions!B2:B12248,Predictions!F2:F12248,">="&B2,Predictions!F2:F12248,"<="&C2) | H2: =AVERAGEIFS(Predictions!C2:C12248,Predictions!F2:F12248,">="&B2,Predictions!F2:F12248,"<="&C2)
A3: 1 | B3: 22001 | C3: 32075 | D3: =COUNTIFS(Predictions!F2:F12248,">="&B3,Predictions!F2:F12248,"<="&C3) | E3: =AVERAGEIFS(Predictions!D2:D12248,Predictions!F2:F12248,">="&B3,Predictions!F2:F12248,"<="&C3) | F3: =AVERAGEIFS(Predictions!E2:E12248,Predictions!F2:F12248,">="&B3,Predictions!F2:F12248,"<="&C3) | G3: =AVERAGEIFS(Predictions!B2:B12248,Predictions!F2:F12248,">="&B3,Predictions!F2:F12248,"<="&C3) | H3: =AVERAGEIFS(Predictions!C2:C12248,Predictions!F2:F12248,">="&B3,Predictions!F2:F12248,"<="&C3)
A4: 2 | B4: 32100 | C4: 43000 | D4: =COUNTIFS(Predictions!F2:F12248,">="&B4,Predictions!F2:F12248,"<="&C4) | E4: =AVERAGEIFS(Predictions!D2:D12248,Predictions!F2:F12248,">="&B4,Predictions!F2:F12248,"<="&C4) | F4: =AVERAGEIFS(Predictions!E2:E12248,Predictions!F2:F12248,">="&B4,Predictions!F2:F12248,"<="&C4) | G4: =AVERAGEIFS(Predictions!B2:B12248,Predictions!F2:F12248,">="&B4,Predictions!F2:F12248,"<="&C4) | H4: =AVERAGEIFS(Predictions!C2:C12248,Predictions!F2:F12248,">="&B4,Predictions!F2:F12248,"<="&C4)
A5: 3 | B5: 43001 | C5: 53097 | D5: =COUNTIFS(Predictions!F2:F12248,">="&B5,Predictions!F2:F12248,"<="&C5) | E5: =AVERAGEIFS(Predictions!D2:D12248,Predictions!F2:F12248,">="&B5,Predictions!F2:F12248,"<="&C5) | F5: =AVERAGEIFS(Predictions!E2:E12248,Predictions!F2:F12248,">="&B5,Predictions!F2:F12248,"<="&C5) | G5: =AVERAGEIFS(Predictions!B2:B12248,Predictions!F2:F12248,">="&B5,Predictions!F2:F12248,"<="&C5) | H5: =AVERAGEIFS(Predictions!C2:C12248,Predictions!F2:F12248,">="&B5,Predictions!F2:F12248,"<="&C5)
A6: 4 | B6: 53098 | C6: 67520 | D6: =COUNTIFS(Predictions!F2:F12248,">="&B6,Predictions!F2:F12248,"<="&C6) | E6: =AVERAGEIFS(Predictions!D2:D12248,Predictions!F2:F12248,">="&B6,Predictions!F2:F12248,"<="&C6) | F6: =AVERAGEIFS(Predictions!E2:E12248,Predictions!F2:F12248,">="&B6,Predictions!F2:F12248,"<="&C6) | G6: =AVERAGEIFS(Predictions!B2:B12248,Predictions!F2:F12248,">="&B6,Predictions!F2:F12248,"<="&C6) | H6: =AVERAGEIFS(Predictions!C2:C12248,Predictions!F2:F12248,">="&B6,Predictions!F2:F12248,"<="&C6)
A7: 5 | B7: 67550 | C7: 85699 | D7: =COUNTIFS(Predictions!F2:F12248,">="&B7,Predictions!F2:F12248,"<="&C7) | E7: =AVERAGEIFS(Predictions!D2:D12248,Predictions!F2:F12248,">="&B7,Predictions!F2:F12248,"<="&C7) | F7: =AVERAGEIFS(Predictions!E2:E12248,Predictions!F2:F12248,">="&B7,Predictions!F2:F12248,"<="&C7) | G7: =AVERAGEIFS(Predictions!B2:B12248,Predictions!F2:F12248,">="&B7,Predictions!F2:F12248,"<="&C7) | H7: =AVERAGEIFS(Predictions!C2:C12248,Predictions!F2:F12248,">="&B7,Predictions!F2:F12248,"<="&C7)
A8: 6 | B8: 85710 | C8: 110062 | D8: =COUNTIFS(Predictions!F2:F12248,">="&B8,Predictions!F2:F12248,"<="&C8) | E8: =AVERAGEIFS(Predictions!D2:D12248,Predictions!F2:F12248,">="&B8,Predictions!F2:F12248,"<="&C8) | F8: =AVERAGEIFS(Predictions!E2:E12248,Predictions!F2:F12248,">="&B8,Predictions!F2:F12248,"<="&C8) | G8: =AVERAGEIFS(Predictions!B2:B12248,Predictions!F2:F12248,">="&B8,Predictions!F2:F12248,"<="&C8) | H8: =AVERAGEIFS(Predictions!C2:C12248,Predictions!F2:F12248,">="&B8,Predictions!F2:F12248,"<="&C8)
A9: 7 | B9: 110071 | C9: 148420 | D9: =COUNTIFS(Predictions!F2:F12248,">="&B9,Predictions!F2:F12248,"<="&C9) | E9: =AVERAGEIFS(Predictions!D2:D12248,Predictions!F2:F12248,">="&B9,Predictions!F2:F12248,"<="&C9) | F9: =AVERAGEIFS(Predictions!E2:E12248,Predictions!F2:F12248,">="&B9,Predictions!F2:F12248,"<="&C9) | G9: =AVERAGEIFS(Predictions!B2:B12248,Predictions!F2:F12248,">="&B9,Predictions!F2:F12248,"<="&C9) | H9: =AVERAGEIFS(Predictions!C2:C12248,Predictions!F2:F12248,">="&B9,Predictions!F2:F12248,"<="&C9)
A10: 8 | B10: 148485 | C10: 213700 | D10: =COUNTIFS(Predictions!F2:F12248,">="&B10,Predictions!F2:F12248,"<="&C10) | E10: =AVERAGEIFS(Predictions!D2:D12248,Predictions!F2:F12248,">="&B10,Predictions!F2:F12248,"<="&C10) | F10: =AVERAGEIFS(Predictions!E2:E12248,Predictions!F2:F12248,">="&B10,Predictions!F2:F12248,"<="&C10) | G10: =AVERAGEIFS(Predictions!B2:B12248,Predictions!F2:F12248,">="&B10,Predictions!F2:F12248,"<="&C10) | H10: =AVERAGEIFS(Predictions!C2:C12248,Predictions!F2:F12248,">="&B10,Predictions!F2:F12248,"<="&C10)
A11: 9 | B11: 213760 | C11: 1672866 | D11: =COUNTIFS(Predictions!F2:F12248,">="&B11,Predictions!F2:F12248,"<="&C11) | E11: =AVERAGEIFS(Predictions!D2:D12248,Predictions!F2:F12248,">="&B11,Predictions!F2:F12248,"<="&C11) | F11: =AVERAGEIFS(Predictions!E2:E12248,Predictions!F2:F12248,">="&B11,Predictions!F2:F12248,"<="&C11) | G11: =AVERAGEIFS(Predictions!B2:B12248,Predictions!F2:F12248,">="&B11,Predictions!F2:F12248,"<="&C11) | H11: =AVERAGEIFS(Predictions!C2:C12248,Predictions!F2:F12248,">="&B11,Predictions!F2:F12248,"<="&C11)
A12: Total | D12: =SUM(D2:D11)
A14: Positive mean residual = model under-predicts that income band on average (README §4.2 bias check).
